{
  "domain": "app-actions-example",
  "intents": [
    {
      "name": "navigate.settings",
      "description": "the user wishes to view the settings screen",
      "implicit_slots": [],
      "slots": []
    },
    {
      "name": "command.control_device",
      "description": "the user wishes to turn a device on or off",
      "implicit_slots": [],
      "slots": [
        {
          "name": "device",
          "capture_name": "device",
          "description": "",
          "type": "entity",
          "facets": "{}"
        },
        {
          "name": "command",
          "capture_name": "command",
          "description": "",
          "type": "entity",
          "facets": "{}"
        }
      ]
    },
    {
      "name": "command.search",
      "description": "the user wishes to search for an item",
      "implicit_slots": [],
      "slots": [
        {
          "name": "item",
          "capture_name": "item",
          "description": "",
          "type": "entity",
          "facets": "{}"
        }
      ]
    }
  ],
  "tags": [
    "o",
    "b_command",
    "b_device",
    "b_item",
    "i_command",
    "i_device",
    "i_item"
  ]
}